{
  "id": 1157683,
  "name": "Cyberdark Invasion",
  "is_illegal": false,
  "is_custom": false,
  "text": "Once per turn: You can activate 1 of these effects;\n\u25cf Target 1 \"Cyberdark\" Effect Monster you control; equip 1 Dragon or Machine monster from either GY to it as an Equip Spell that gives it 1000 ATK.\n\u25cf Send 1 Equip Card you control equipped to a Machine monster to the GY; destroy 1 card your opponent controls.\nYou can only use each effect of \"Cyberdark Invasion\" once per turn.",
  "images": [
    "https://images.ygoprodeck.com/images/cards/1157683.jpg"
  ],
  "type": "Trap",
  "trap_type": "Continuous"
}