{
  "id": 300201009,
  "name": "Millennium Eye (Skill Card)",
  "is_illegal": false,
  "is_custom": false,
  "text": "",
  "skill_activation": "Flip this card over when you activate this Skill.",
  "skill_effect": "At the start of the Duel, look at your opponent\u0027s opening hand.\nYou may choose to have that player shuffle their hand into their Deck and draw a new hand. (If both players use a Skill at the same time, the Turn player resolves their Skill first.)",
  "images": [
    "https://images.ygoprodeck.com/images/cards/300201009.jpg"
  ],
  "type": "Skill",
  "skill_type": "",
  "character": "Maximillion Pegasus"
}
