{
  "id": 83308376,
  "name": "Swordsoul Punishment",
  "is_illegal": false,
  "is_custom": false,
  "text": "If you control a Synchro Monster: Target 1 card on the field or in either GY; banish it. If your opponent controls a Ritual, Fusion, Synchro, Xyz, or Link Monster: You can banish 1 Synchro Monster from your GY; add this card from the GY to your hand. You can only use each effect of \"Swordsoul Punishment\" once per turn.",
  "images": [
    "https://images.ygoprodeck.com/images/cards/83308376.jpg"
  ],
  "type": "Spell",
  "spell_type": "Normal"
}