{
  "name": "Light of Destruction (Boosted Box)",
  "code": "LODT_BRB",
  "type": "Boosted Booster Box (Series 5)",
  "date": "13-05-2008",
  "image": "https://raw.githubusercontent.com/maugameslol/MAU-YDM2-CUSTOM-IMAGES/main/ProductImages/Boxes/LODT_1st_ed_box.jpg",
  "pull_type": "composition",
  "sub_sets": [
    "LODT",
    "LODT",
    "LODT",
    "LODT",
    "LODT",
    "LODT",
    "LODT",
    "LODT",
    "LODT",
    "LODT",
    "LODT",
    "LODT",
    "LODT_SR",
    "LODT_SR",
    "LODT_SR",
    "LODT_SR",
    "LODT_SR",
    "LODT_SR",
    "LODT_UR",
    "LODT_UR",
    "LODT_UR",
    "LODT_UR",
    "LODT_SCR",
    "LODT_SCR"
  ]
}
