{
  "name": "Yu-Gi-Oh! The Falsebound Kingdom",
  "code": "TFK",
  "type": "Video Game Promotional Cards",
  "date": "04-11-2003",
  "image": "https://ms.yugipedia.com//0/05/TFK-VideoGameNA.png",
  "pull_type": "full",
  "cards": [
    {
      "id": 24311372,
      "code": "TFK-001",
      "rarity": "Prismatic Secret Rare",
      "image_index": 1
    },
    {
      "id": 50705071,
      "code": "TFK-002",
      "rarity": "Prismatic Secret Rare",
      "image_index": 0
    },
    {
      "id": 4149689,
      "code": "TFK-003",
      "rarity": "Prismatic Secret Rare",
      "image_index": 1
    }
  ]
}